hyperframes/hyperframe.py
hyperframes-0.0.1.dist-info/LICENSE.txt
hyperframes-0.0.1.dist-info/entry_points.txt
hyperframes-0.0.1.dist-info/WHEEL
hyperframes-0.0.1.dist-info/METADATA
hyperframes-0.0.1.dist-info/RECORD
