Metadata-Version: 2.1
Name: hyperframes
Version: 0.0.1
Summary: Labeled high dimensional matrix access
Home-page: https://github.com/0xideas/hyperframe
License: MIT
Keywords: data,data storage,matrix,high dimensional data
Author: Leon Luithlen
Author-email: leontimnaluithlen@gmail.com
Requires-Python: >=3.9.0,<4.0.0
Classifier: License :: OSI Approved :: MIT License
Classifier: Programming Language :: Python :: 3
Classifier: Programming Language :: Python :: 3.9
Classifier: Programming Language :: Python :: 3.10
Classifier: Programming Language :: Python :: 3.11
Requires-Dist: numpy (>=1.19.5,<2.0.0)
Requires-Dist: pandas (>=1.1.4,<2.0.0)
Project-URL: Repository, https://github.com/0xideas/hyperframe
